
    {'date':"2020-10-25 16:24:12.726312",
      'dataset': [ {
    "humidity":68.00,
    "temp":17.00,
    "HIC":16.53,
    "light":696
},{
    "humidity":68.00,
    "temp":17.00,
    "HIC":16.53,
    "light":695
},{
    "humidity":68.00,
    "temp":17.00,
    "HIC":16.53,
    "light":695
},{
    "humidity":68.00,
    "temp":17.00,
    "HIC":16.53,
    "light":694
},{
    "humidity":68.00,
    "temp":17.10,
    "HIC":16.64,
    "light":693
},{
    "humidity":68.00,
    "temp":17.10,
    "HIC":16.64,
    "light":692
},{
    "humidity":68.00,
    "temp":17.00,
    "HIC":16.53,
    "light":691
},{
    "humidity":68.00,
    "temp":17.00,
    "HIC":16.53,
    "light":690
},{
    "humidity":68.00,
    "temp":17.00,
    "HIC":16.53,
    "light":688
},{
    "humidity":68.00,
    "temp":17.00,
    "HIC":16.53,
    "light":687
},{
    "humidity":68.00,
    "temp":17.00,
    "HIC":16.53,
    "light":687
},{
    "humidity":68.00,
    "temp":17.10,
    "HIC":16.64,
    "light":685
},{
    "humidity":68.00,
    "temp":17.00,
    "HIC":16.53,
    "light":683
},{
    "humidity":68.00,
    "temp":17.10,
    "HIC":16.64,
    "light":684
},{
    "humidity":68.00,
    "temp":17.00,
    "HIC":16.53,
    "light":681
},{
    "humidity":68.00,
    "temp":16.90,
    "HIC":16.42,
    "light":682
},{
    "humidity":68.00,
    "temp":17.00,
    "HIC":16.53,
    "light":680
},{
    "humidity":68.00,
    "temp":17.00,
    "HIC":16.53,
    "light":679
},{
    "humidity":68.00,
    "temp":17.00,
    "HIC":16.53,
    "light":677
},{
    "humidity":68.00,
    "temp":17.00,
    "HIC":16.53,
    "light":677
},{
    "humidity":68.00,
    "temp":17.00,
    "HIC":16.53,
    "light":676
},{
    "humidity":68.00,
    "temp":17.00,
    "HIC":16.53,
    "light":675
},{
    "humidity":68.00,
    "temp":17.00,
    "HIC":16.53,
    "light":675
},{
    "humidity":68.00,
    "temp":17.00,
    "HIC":16.53,
    "light":674
},{
    "humidity":68.00,
    "temp":17.00,
    "HIC":16.53,
    "light":672
},{
    "humidity":68.00,
    "temp":17.00,
    "HIC":16.53,
    "light":671
},{
    "humidity":68.00,
    "temp":17.00,
    "HIC":16.53,
    "light":670
},{
    "humidity":68.00,
    "temp":17.00,
    "HIC":16.53,
    "light":669
},{
    "humidity":68.00,
    "temp":17.00,
    "HIC":16.53,
    "light":669
},{
    "humidity":68.00,
    "temp":17.00,
    "HIC":16.53,
    "light":668
},{
    "humidity":68.00,
    "temp":17.00,
    "HIC":16.53,
    "light":668
},{
    "humidity":68.00,
    "temp":17.00,
    "HIC":16.53,
    "light":666
},{
    "humidity":68.00,
    "temp":17.10,
    "HIC":16.64,
    "light":665
},{
    "humidity":68.00,
    "temp":17.00,
    "HIC":16.53,
    "light":664
},{
    "humidity":68.00,
    "temp":17.00,
    "HIC":16.53,
    "light":663
},{
    "humidity":68.00,
    "temp":17.00,
    "HIC":16.53,
    "light":661
},{
    "humidity":68.00,
    "temp":17.00,
    "HIC":16.53,
    "light":661
},{
    "humidity":68.00,
    "temp":17.00,
    "HIC":16.53,
    "light":659
},{
    "humidity":68.00,
    "temp":17.10,
    "HIC":16.64,
    "light":659
},{
    "humidity":68.00,
    "temp":17.00,
    "HIC":16.53,
    "light":657
},{
    "humidity":68.00,
    "temp":17.00,
    "HIC":16.53,
    "light":656
},{
    "humidity":68.00,
    "temp":17.10,
    "HIC":16.64,
    "light":655
},{
    "humidity":68.00,
    "temp":17.00,
    "HIC":16.53,
    "light":655
},{
    "humidity":68.00,
    "temp":17.00,
    "HIC":16.53,
    "light":654
},{
    "humidity":68.00,
    "temp":17.00,
    "HIC":16.53,
    "light":652
},{
    "humidity":68.00,
    "temp":17.00,
    "HIC":16.53,
    "light":652
},{
    "humidity":68.00,
    "temp":17.00,
    "HIC":16.53,
    "light":651
},{
    "humidity":68.00,
    "temp":17.00,
    "HIC":16.53,
    "light":650
},{
    "humidity":68.00,
    "temp":17.00,
    "HIC":16.53,
    "light":651
},{
    "humidity":68.00,
    "temp":17.10,
    "HIC":16.64,
    "light":650
},{
    "humidity":68.00,
    "temp":17.00,
    "HIC":16.53,
    "light":650
},{
    "humidity":68.00,
    "temp":17.00,
    "HIC":16.53,
    "light":649
},{
    "humidity":68.00,
    "temp":16.90,
    "HIC":16.42,
    "light":649
},{
    "humidity":68.00,
    "temp":17.10,
    "HIC":16.64,
    "light":648
},{
    "humidity":68.00,
    "temp":17.00,
    "HIC":16.53,
    "light":648
},{
    "humidity":68.00,
    "temp":17.00,
    "HIC":16.53,
    "light":648
},{
    "humidity":68.00,
    "temp":17.00,
    "HIC":16.53,
    "light":647
},{
    "humidity":68.00,
    "temp":17.00,
    "HIC":16.53,
    "light":647
},{
    "humidity":68.00,
    "temp":17.00,
    "HIC":16.53,
    "light":647
},{
    "humidity":68.00,
    "temp":17.10,
    "HIC":16.64,
    "light":646
},]}